.ansible-droplet-inventory
LICENSE
MANIFEST.in
README.md
setup.py
ansible_droplet/__init__.py
ansible_droplet/cli.py
ansible_droplet.egg-info/PKG-INFO
ansible_droplet.egg-info/SOURCES.txt
ansible_droplet.egg-info/dependency_links.txt
ansible_droplet.egg-info/not-zip-safe
ansible_droplet.egg-info/requires.txt
ansible_droplet.egg-info/top_level.txt
ansible_droplet/ansible/ansible.cfg
ansible_droplet/ansible/create-droplet-playbook.yml
ansible_droplet/ansible/delete-droplet-playbook.yml
ansible_droplet/ansible/requirements.yml
ansible_droplet/ansible/droplet_specs/micro.yaml
ansible_droplet/ansible/droplet_specs/mini.yaml
ansible_droplet/ansible/droplet_specs/power.yaml
ansible_droplet/ansible/inventory/localhost
ansible_droplet/ansible/roles/roles-on-droplet/create-new-sudo-user/tasks/main.yml
ansible_droplet/ansible/roles/roles-on-droplet/glances/tasks/main.yml
ansible_droplet/ansible/roles/roles-on-droplet/glances/templates/glances.service
ansible_droplet/ansible/roles/roles-on-localhost/load-droplet-specs/defaults/main.yml
ansible_droplet/ansible/roles/roles-on-localhost/load-droplet-specs/tasks/main.yml
bin/ansible-droplet