Metadata-Version: 1.1
Name: ansible-droplet
Version: 0.4.7
Summary: A cli to Create / Destroy DigitalOcean Droplets
Home-page: https://github.com/FlorianKempenich/ansible-droplet
Author: Florian Kempenich & Antonio Pires
Author-email: Flori@nKempenich.com
License: MIT
Keywords: digitalocean digital ocean droplet ansible ssh provision
Platform: UNKNOWN
Classifier: Environment :: Console
Classifier: Intended Audience :: Developers
Classifier: License :: OSI Approved :: MIT License
Classifier: Topic :: System :: Installation/Setup
Classifier: Topic :: System :: Systems Administration
Classifier: Topic :: Utilities
